pbpy/__init__.py
pbpy/client.py
pbpy/errors.py
pbpy-1.0.1.dist-info/LICENSE.txt
pbpy-1.0.1.dist-info/METADATA
pbpy-1.0.1.dist-info/WHEEL
pbpy-1.0.1.dist-info/top_level.txt
pbpy-1.0.1.dist-info/RECORD
