Metadata-Version: 2.1
Name: pbpy
Version: 1.0.1
Summary: Wrapper per l'api di primebots.it
Home-page: https://pypi.org/project/pbpy
Author: Giuseppe Pollio
Author-email: polliog@protonmail.com
License: MIT
Download-URL: https://github.com/Polliog/primebots-py-wrapper
Keywords: primebots,pbpy
Platform: UNKNOWN
Requires-Dist: logging
Requires-Dist: requests
Requires-Dist: discord.py
Requires-Dist: asyncio
Requires-Dist: python-socketio[asyncio_client]
